Workbook

Sheet Lisez-moi
A1: Le tri des prélèvements
A2: 420 prélèvements obligatoires recensés, un par un, et le sort que la refonte fiscale de Résolution réserve à chacun.
A4: Les six sorts
A5: Conservé et absorbe — L’un des quatre impôts que la refonte garde : taxe sur la valeur ajoutée, impôt sur le revenu, impôt sur les sociétés, taxe foncière. Il reprend le produit des prélèvements fondus en lui.
A6: Fondu par rattachement — Le prélèvement disparaît ; son produit est repris par l’impôt conservé qui porte la même assiette (colonne « Impôt qui le reprend »).
A7: Fondu dans l’équilibre — Le prélèvement disparaît ; son produit est repris par les hausses d’équilibre des quatre impôts conservés, sans rattachement à l’un d’eux.
A8: Maintenu à part — Le prélèvement demeure, en complément de l’impôt qu’il prolonge (colonne « Impôt qui le reprend »).
A9: Cotisations sociales à unifier — Les cotisations sociales ne relèvent pas de la refonte fiscale : elles sont isolées, pour être unifiées.
A10: Hors champ — Recette publique qui n’est pas un prélèvement obligatoire (produit d’enchères, recette non fiscale) : recensée, non triée.
A12: Lire le tri
A13: Assiette : la matière taxée — les cotisations sociales, les contributions sociales sur les revenus, la masse salariale, le revenu des personnes, l’activité des entreprises, la consommation, la propriété.
A14: Rendement 2026 : ce que l’État publie, prélèvement par prélèvement. Une case vide ne vaut pas zéro : l’État ne publie pas le rendement de 186 prélèvements sur 420, cotisations sociales et taxes affectées à des organismes pour l’essentiel.
... A19: Calculs et tri : Résolution.

Sheet Tri
A1: Prélèvement | B1: Nature | C1: Assiette | D1: Sous-catégorie | E1: Poste du schéma de refonte | F1: Sort | G1: Impôt qui le reprend | H1: Rendement 2026 (M€) | I1: Bénéficiaire | J1: Siège juridique
A2: Cotisation obligatoire des collectivités aux centres de gestion de la fonction publique territoriale | B2: cotisation sociale | C2: 1. Les cotisations sociales | D2: Cotisations de sécurité sociale — régime général | F2: Cotisations sociales à unifier | H2: 691.8 | I2: Centres de gestion de la fonction publique territoriale ; Comité de gestion des œuvres sociales des personnels hospitaliers (CGOS) | J2: Code général de la fonction publique, art. L. 452-25
A3: Cotisation obligatoire des collectivités au Centre national de la fonction publique territoriale | B3: cotisation sociale | C3: 1. Les cotisations sociales | D3: Cotisations de sécurité sociale — régime général | F3: Cotisations sociales à unifier | H3: 413 | I3: Centre national de la fonction publique territoriale (CNFPT) | J3: Code général de la fonction publique, art. L. 451-17
A4: Contribution des employeurs de main-d'œuvre étrangère permanente | B4: cotisation sociale | C4: 1. Les cotisations sociales | D4: Cotisations de sécurité sociale — régime général | F4: Cotisations sociales à unifier | J4: Art. L. 436-10 du code de l'entrée et du séjour des étrangers et du droit d'asile
A5: Contribution des employeurs de main-d'œuvre étrangère saisonnière | B5: cotisation sociale | C5: 1. Les cotisations sociales | D5: Cotisations de sécurité sociale — régime général | F5: Cotisations sociales à unifier | J5: Art. L. 436-10 du code de l'entrée et du séjour des étrangers et du droit d'asile
A6: Contribution des employeurs de main-d'œuvre étrangère temporaire | B6: cotisation sociale | C6: 1. Les cotisations sociales | D6: Cotisations de sécurité sociale — régime général | F6: Cotisations sociales à unifier | J6: Art. L. 436-10 du code de l'entrée et du séjour des étrangers et du droit d'asile
A7: Contribution sur les indemnités de rupture conventionnelle | B7: contribution sociale | C7: 2. Les contributions sociales sur les revenus | D7: Contributions sur les indemnités de rupture | E7: Taxes sur la main d'œuvre | F7: Fondu dans l’équilibre | J7: Code de la sécurité sociale, art. L. 137-15
A8: Cotisation des employeurs | B8: cotisation sociale | C8: 1. Les cotisations sociales | D8: Cotisations de sécurité sociale — régime général | F8: Cotisations sociales à unifier | I8: FNAL - Fonds national d'aide au logement | J8: Code de la construction et de l'habitation, art. L. 813-4
A9: Cotisations avantages spécifiques IEG | B9: cotisation sociale | C9: 1. Les cotisations sociales | D9: Cotisations de sécurité sociale — régime général | F9: Cotisations sociales à unifier | J9: Code de la sécurité sociale, art. L. 243-5
A10: Cotisations salariales — Autres régimes | B10: cotisation sociale | C10: 1. Les cotisations sociales | D10: Cotisations de sécurité sociale — régime général | F10: Cotisations sociales à unifier | J10: Code de la sécurité sociale, art. L. 241-3
A11: Cotisations salariales — Régime général et FSV | B11: cotisation sociale | C11: 1. Les cotisations sociales | D11: Cotisations de sécurité sociale — régime général | F11: Cotisations sociales à unifier | J11: Code de la sécurité sociale, art. L. 241-3
A12: Cotisations sociales - brutes BdF — Autres régimes | B12: cotisation sociale | C12: 1. Les cotisations sociales | D12: Cotisations de sécurité sociale — régime général | F12: Cotisations sociales à unifier | J12: Code de la sécurité sociale, art. L. 241-3
A13: Contribution sur les indemnités de mise à la retraite | B13: contribution sociale | C13: 2. Les contributions sociales sur les revenus | D13: Contributions sur les indemnités de rupture | E13: Taxes sur la main d'œuvre | F13: Fondu dans l’équilibre | H13: 895 | I13: CNAV | J13: Code de la sécurité sociale, art. L. 137-12
A14: Contribution sur les régimes de retraite conditionnant la constitution de droits à prestations à l’achèvement de la carrière du bénéficiaire dans l’entreprise | B14: cotisation sociale | C14: 1. Les cotisations sociales | D14: Vieillesse et régimes spéciaux | F14: Cotisations sociales à unifier | H14: 179 | I14: CNAV | J14: Code de la sécurité sociale, art. L. 137-11
A15: Contribution sur les avantages de préretraite d’entreprise | B15: cotisation sociale | C15: 1. Les cotisations sociales | D15: Vieillesse et régimes spéciaux | F15: Cotisations sociales à unifier | H15: 34 | I15: CNAV | J15: Code de la sécurité sociale, art. L. 137-10
A16: Autres cotisations sociales Vieillesse — Régime des salariés agricoles | B16: cotisation sociale | C16: 1. Les cotisations sociales | D16: Vieillesse et régimes spéciaux | F16: Cotisations sociales à unifier | J16: Code de la sécurité sociale, art. L. 243-5
A17: Autres cotisations sociales et majorations Vieillesse — Régime spécial des industries électriques et gazières (CNIEG) | B17: cotisation sociale | C17: 1. Les cotisations sociales | D17: Vieillesse et régimes spéciaux | F17: Cotisations sociales à unifier | J17: Code de la sécurité sociale, art. L. 243-5
A18: Autres cotisations sociales vieillesse — Régime général et FSV | B18: cotisation sociale | C18: 1. Les cotisations sociales | D18: Vieillesse et régimes spéciaux | F18: Cotisations sociales à unifier | J18: Code de la sécurité sociale, art. L. 241-2
A19: Autres cotisations, majorations et pénalités — Régime spécial des fonctionnaires territoriaux et hospitaliers | B19: cotisation sociale | C19: 1. Les cotisations sociales | D19: Vieillesse et régimes spéciaux | F19: Cotisations sociales à unifier | J19: Code de la sécurité sociale, art. L. 243-5
A20: Contributions d'équilibre de l'employeur principal Régime SNCF | B20: cotisation sociale | C20: 1. Les cotisations sociales | D20: Vieillesse et régimes spéciaux | F20: Cotisations sociales à unifier | J20: Code de la sécurité sociale, art. L. 137-15
A21: Cotisations Vieillesse salariés — Régime de retraite des fonctionnaires civils et militaires de l'État | B21: cotisation sociale | C21: 1. Les cotisations sociales | D21: Vieillesse et régimes spéciaux | F21: Cotisations sociales à unifier | J21: Code de la sécurité sociale, art. L. 241-3
A22: Cotisations Vieillesse salariés — Régime des salariés agricoles | B22: cotisation sociale | C22: 1. Les cotisations sociales | D22: Vieillesse et régimes spéciaux | F22: Cotisations sociales à unifier | J22: Code de la sécurité sociale, art. L. 241-2
A23: Cotisations Vieillesse — Régime des salariés agricoles | B23: cotisation sociale | C23: 1. Les cotisations sociales | D23: Vieillesse et régimes spéciaux | F23: Cotisations sociales à unifier | J23: Code de la sécurité sociale, art. L. 241-3
A24: Cotisations d'équilibre de l'employeur principal — Régime spécial des fonctionnaires territoriaux et hospitaliers | B24: cotisation sociale | C24: 1. Les cotisations sociales | D24: Vieillesse et régimes spéciaux | F24: Cotisations sociales à unifier | J24: Code de la sécurité sociale, art. L. 241-2
A25: Cotisations patronales "vieillesse" non plafonnées Vieillesse — Régime spécial des industries électriques et gazières (CNIEG) | B25: cotisation sociale | C25: 1. Les cotisations sociales | D25: Vieillesse et régimes spéciaux | F25: Cotisations sociales à unifier | J25: Code de la sécurité sociale, art. L. 241-2
A26: Cotisations patronales Vieillesse — Caisse autonome nationale de sécurité sociale dans les mines | B26: cotisation sociale | C26: 1. Les cotisations sociales | D26: Vieillesse et régimes spéciaux | F26: Cotisations sociales à unifier | J26: Code de la sécurité sociale, art. L. 241-2
A27: Cotisations patronales Vieillesse — Régime spécial des agents de la RATP | B27: cotisation sociale | C27: 1. Les cotisations sociales | D27: Vieillesse et régimes spéciaux | F27: Cotisations sociales à unifier | J27: Code de la sécurité sociale, art. L. 241-2
... A43: Contribution de l'employeur principal AT-MP — Régime spécial des industries électriques et gazières (CNIEG) | B43: cotisation sociale | C43: 1. Les cotisations sociales | D43: Maladie, famille, accidents et prévoyance | F43: Cotisations sociales à unifier | J43: Code de la sécurité sociale, art. L. 241-2
A44: Cotisation au profit des caisses d’assurances d’accidents agricoles d’Alsace-Moselle | B44: cotisation sociale | C44: 1. Les cotisations sociales | D44: Maladie, famille, accidents et prévoyance | F44: Cotisations sociales à unifier | I44: CAAA - Caisses d'assurances d'accidents agricoles d'Alsace-Moselle | J44: Code rural et de la pêche maritime, art. L. 761-5
A45: Cotisations AT-MP salariés — Régime de retraite des fonctionnaires civils et militaires de l'État | B45: cotisation sociale | C45: 1. Les cotisations sociales | D45: Maladie, famille, accidents et prévoyance | F45: Cotisations sociales à unifier | J45: Code de la sécurité sociale, art. L. 241-2
A46: Cotisations AT-MP salariés — Régime des salariés agricoles | B46: cotisation sociale | C46: 1. Les cotisations sociales | D46: Maladie, famille, accidents et prévoyance | F46: Cotisations sociales à unifier | J46: Code de la sécurité sociale, art. L. 241-2
A47: Cotisations AT-MP salariés — Régime général +FSV | B47: cotisation sociale | C47: 1. Les cotisations sociales | D47: Maladie, famille, accidents et prévoyance | F47: Cotisations sociales à unifier | J47: Code de la sécurité sociale, art. L. 241-2
A48: Cotisations Famille salariés — Régime général +FSV | B48: cotisation sociale | C48: 1. Les cotisations sociales | D48: Maladie, famille, accidents et prévoyance | F48: Cotisations sociales à unifier | J48: Code de la sécurité sociale, art. L. 241-2
A49: Cotisations IJ exploitants | B49: cotisation sociale | C49: 1. Les cotisations sociales | D49: Maladie, famille, accidents et prévoyance | F49: Cotisations sociales à unifier | J49: Code de la sécurité sociale, art. L. 243-5
A50: Cotisations Maladie salariés — Régime général +FSV | B50: cotisation sociale | C50: 1. Les cotisations sociales | D50: Maladie, famille, accidents et prévoyance | F50: Cotisations sociales à unifier | J50: Code de la sécurité sociale, art. L. 241-2
A51: Cotisations décès - CIPAV | B51: cotisation sociale | C51: 1. Les cotisations sociales | D51: Maladie, famille, accidents et prévoyance | F51: Cotisations sociales à unifier | J51: Code de la sécurité sociale, art. L. 243-5
A52: Cotisations décès - CNIEG | B52: cotisation sociale | C52: 1. Les cotisations sociales | D52: Maladie, famille, accidents et prévoyance | F52: Cotisations sociales à unifier | J52: Code de la sécurité sociale, art. L. 243-5
A53: Cotisations institutions de prévoyance | B53: cotisation sociale | C53: 1. Les cotisations sociales | D53: Maladie, famille, accidents et prévoyance | F53: Cotisations sociales à unifier | J53: Code de la sécurité sociale, art. L. 243-5
A54: Cotisations invalidité - CIPAV | B54: cotisation sociale | C54: 1. Les cotisations sociales | D54: Maladie, famille, accidents et prévoyance | F54: Cotisations sociales à unifier | J54: Code de la sécurité sociale, art. L. 243-5
A55: Cotisations invalidité - CNIEG | B55: cotisation sociale | C55: 1. Les cotisations sociales | D55: Maladie, famille, accidents et prévoyance | F55: Cotisations sociales à unifier | J55: Code de la sécurité sociale, art. L. 243-5
A56: Cotisations patronales "décès" Vieillesse — Régime spécial des industries électriques et gazières (CNIEG) | B56: cotisation sociale | C56: 1. Les cotisations sociales | D56: Maladie, famille, accidents et prévoyance | F56: Cotisations sociales à unifier | J56: Code de la sécurité sociale, art. L. 241-2
... A84: Autres cotisations et contributions sociales diverses FSV — Régime des salariés agricoles | B84: cotisation sociale | C84: 1. Les cotisations sociales | D84: Autres cotisations, majorations et pénalités | F84: Cotisations sociales à unifier | J84: Code de la sécurité sociale, art. L. 241-2
A85: Contribution sociale généralisée (CSG) | B85: contribution sociale | C85: 2. Les contributions sociales sur les revenus | D85: Contribution sociale généralisée et CRDS | F85: Fondu par rattachement | G85: Impôt sur le revenu | H85: 155467.8 | I85: CNAF ; CNAMTS ; CNAV ; CNSA ; Caisse d'amortissement de la dette sociale (CADES) ; FSV ; UNEDIC | J85: Code de la sécurité sociale, art. L. 136-1
A86: Contributions pour le remboursement de la dette sociale (CRDS) | B86: contribution sociale | C86: 2. Les contributions sociales sur les revenus | D86: Contribution sociale généralisée et CRDS | F86: Fondu par rattachement | G86: Impôt sur le revenu | H86: 9350.4 | I86: Caisse d'amortissement de la dette sociale (CADES) | J86: Code général des impôts, art. 1600-0 G
A87: Prélèvements de solidarité | B87: contribution sociale | C87: 2. Les contributions sociales sur les revenus | D87: Prélèvements sociaux sur les revenus du capital | F87: Fondu par rattachement | G87: Impôt sur le revenu | H87: 15634.9 | I87: Budget général de l'État | J87: Art. 235 ter du code général des impôts
A88: Contributions sociales maladie - Prélèvement social sur les revenus du capital | B88: contribution sociale | C88: 2. Les contributions sociales sur les revenus | D88: Prélèvements sociaux sur les revenus du capital | F88: Fondu par rattachement | G88: Impôt sur le revenu | J88: Code de la sécurité sociale, art. L. 136-1
A89: Prélèvement social et de solidarité sur les revenus du capital FSV | B89: contribution sociale | C89: 2. Les contributions sociales sur les revenus | D89: Prélèvements sociaux sur les revenus du capital | F89: Fondu par rattachement | G89: Impôt sur le revenu | J89: Code de la sécurité sociale, art. L. 136-1
A90: Prélèvement social sur les revenus des placements (maladie) | B90: contribution sociale | C90: 2. Les contributions sociales sur les revenus | D90: Prélèvements sociaux sur les revenus du capital | F90: Fondu par rattachement | G90: Impôt sur le revenu | J90: Code de la sécurité sociale, art. L. 136-1
A91: Prélèvement social sur les revenus du capital CNSA | B91: contribution sociale | C91: 2. Les contributions sociales sur les revenus | D91: Prélèvements sociaux sur les revenus du capital | F91: Fondu par rattachement | G91: Impôt sur le revenu | J91: Code de la sécurité sociale, art. L. 136-1
A92: Prélèvement social sur les revenus du patrimoine (branche maladie) | B92: contribution sociale | C92: 2. Les contributions sociales sur les revenus | D92: Prélèvements sociaux sur les revenus du capital | F92: Fondu par rattachement | G92: Impôt sur le revenu | J92: Code de la sécurité sociale, art. L. 136-1
A93: Prélèvement sur les revenus des placements FSV | B93: contribution sociale | C93: 2. Les contributions sociales sur les revenus | D93: Prélèvements sociaux sur les revenus du capital | F93: Fondu par rattachement | G93: Impôt sur le revenu | J93: Code de la sécurité sociale, art. L. 136-1
A94: Prélèvement sur les revenus du patrimoine FSV | B94: contribution sociale | C94: 2. Les contributions sociales sur les revenus | D94: Prélèvements sociaux sur les revenus du capital | F94: Fondu par rattachement | G94: Impôt sur le revenu | J94: Code de la sécurité sociale, art. L. 136-1
A95: Contribution solidarité autonomie (CSA) | B95: contribution sociale | C95: 2. Les contributions sociales sur les revenus | D95: Solidarité autonomie | E95: Forfaits de cotisation | F95: Maintenu à part | H95: 2563.2 | I95: CNSA | J95: Code de la sécurité sociale, art. 137-40
A96: Contribution additionnelle de solidarité autonomie (CASA) | B96: contribution sociale | C96: 2. Les contributions sociales sur les revenus | D96: Solidarité autonomie | F96: Fondu par rattachement | G96: Impôt sur le revenu | H96: 977.1 | I96: CNSA | J96: Code de la sécurité sociale, art. 137-41
A97: Contributions sur avantages de retraite et de préretraite (branche maladie) | B97: contribution sociale | C97: 2. Les contributions sociales sur les revenus | D97: Contributions sur les revenus de remplacement | F97: Fondu par rattachement | G97: Impôt sur le revenu | J97: Code de la sécurité sociale, art. L. 136-1
A98: Contributions sur avantages de retraite et de préretraite FSV | B98: contribution sociale | C98: 2. Les contributions sociales sur les revenus | D98: Contributions sur les revenus de remplacement | F98: Fondu par rattachement | G98: Impôt sur le revenu | J98: Code de la sécurité sociale, art. L. 136-1
A99: Forfait social | B99: contribution sociale | C99: 2. Les contributions sociales sur les revenus | D99: Épargne salariale et actionnariat | E99: Forfaits de cotisation | F99: Maintenu à part | H99: 6690.2 | I99: CNAV | J99: Code de la sécurité sociale, art. L. 137-15
A100: Contributions patronales et salariales sur les attributions d’options (stock-options) de souscription ou d’achat des actions et sur les attributions gratuites | B100: contribution sociale | C100: 2. Les contributions sociales sur les revenus | D100: Épargne salariale et actionnariat | F100: Fondu par rattachement | G100: Impôt sur le revenu | H100: 1669.1 | I100: CNAF | J100: Code de la sécurité sociale, art. L. 137-13
A101: Taxe sur les salaires | B101: taxe sur la masse salariale | C101: 3. Les taxes sur la masse salariale | D101: Taxe sur les salaires | E101: Taxes sur la main d'œuvre | F101: Fondu dans l’équilibre | H101: 17877 | I101: CNAV, CNAF, CNAM et CNSA | J101: Art. L. 131-8, 1° du code de la sécurité sociale et 231 du code général des impôts
A102: Contribution unique à la formation professionnelle et à l'alternance | B102: taxe sur la masse salariale | C102: 3. Les taxes sur la masse salariale | D102: Formation et apprentissage | E102: Taxes sur la main d'œuvre | F102: Fondu dans l’équilibre | H102: 10846.5 | I102: France Compétences | J102: Code du travail, art. L. 6131-2
A103: Solde de la taxe d'apprentissage après prise en compte des versements directs des entreprises mentionnés au II de l'article L. 6241-2 | B103: taxe sur la masse salariale | C103: 3. Les taxes sur la masse salariale | D103: Formation et apprentissage | E103: Taxes sur la main d'œuvre | F103: Fondu dans l’équilibre | H103: 513.1 | I103: Caisse des dépôts et des consignations | J103: Code du travail, art. L. 6241-2 II
A104: PEFPC : CPF CDD (ex-CIF-CDD) : 1% des salaires versés, ou moins en cas d'accord de branche | B104: taxe sur la masse salariale | C104: 3. Les taxes sur la masse salariale | D104: Formation et apprentissage | E104: Taxes sur la main d'œuvre | F104: Fondu dans l’équilibre | H104: 322.9 | I104: France Compétences | J104: Code du travail, art. L. 6331-6
A105: PEFPC : Participation au financement de la formation des professions non salariées (à l'exception des artisans et des exploitants agricoles) correspondant à 0,25% du montant annuel du plafond de la sécurité sociale | B105: taxe sur la masse salariale | C105: 3. Les taxes sur la masse salariale | D105: Formation et apprentissage | E105: Taxes sur la main d'œuvre | F105: Fondu dans l’équilibre | H105: 204 | I105: France Compétences | J105: Art. L. 6331-48, 1° (création) et L. 6331-50 (affectation) du code du travail
A106: Contribution supplémentaire à l'apprentissage | B106: taxe sur la masse salariale | C106: 3. Les taxes sur la masse salariale | D106: Formation et apprentissage | E106: Taxes sur la main d'œuvre | F106: Fondu dans l’équilibre | H106: 190.9 | I106: France Compétences | J106: Code du travail, art. L. 6242-1
A107: Contribution spécifique pour le développement de la formation professionnelle initiale et continue dans les métiers des professions du bâtiment et des travaux publics. | B107: taxe sur la masse salariale | C107: 3. Les taxes sur la masse salariale | D107: Formation et apprentissage | E107: Taxes sur la main d'œuvre | F107: Fondu dans l’équilibre | H107: 131 | I107: Comité de Concertation et de Coordination de l'Apprentissage du Bâtiment et des Travaux Publics (3CABTP) | J107: Code du travail, art. L. 6331-35
A108: PEFPC : Participation au financement de la formation des professions non salariées (artisans) correspondant à 0,29% du montant annuel du plafond de la sécurité sociale, dont micro entrepreneurs | B108: taxe sur la masse salariale | C108: 3. Les taxes sur la masse salariale | D108: Formation et apprentissage | E108: Taxes sur la main d'œuvre | F108: Fondu dans l’équilibre | H108: 95 | I108: France Compétences | J108: Art. L. 6331-48 2° et L. 6331-50 du code du travail
A109: PEFPC : Participation au financement de la formation des intermittents correspondant au minimum à 2% des rémunérations versées | B109: taxe sur la masse salariale | C109: 3. Les taxes sur la masse salariale | D109: Formation et apprentissage | E109: Taxes sur la main d'œuvre | F109: Fondu dans l’équilibre | H109: 69.1 | I109: France Compétences | J109: Code du travail, art. L. 6331-55
A110: Contribution conventionnelle à la formation pour les entreprises de travail temporaire | B110: taxe sur la masse salariale | C110: 3. Les taxes sur la masse salariale | D110: Formation et apprentissage | E110: Taxes sur la main d'œuvre | F110: Fondu dans l’équilibre | H110: 68.5 | I110: Fonds pour l'emploi du travail temporaire | J110: Code du travail, art. L. 6331-69
A111: PEFPC : Participation au financement de la formation des professions non salariées (Entreprises du Vivant, agriculture) correspondant à 0,30 % des revenus professionnels ou de l'assiette forfaitaire déterminés à l'article L. 731-16 du code rural et de la pêche maritime | B111: taxe sur la masse salariale | C111: 3. Les taxes sur la masse salariale | D111: Formation et apprentissage | E111: Taxes sur la main d'œuvre | F111: Fondu dans l’équilibre | H111: 60.7 | I111: France Compétences | J111: Code du travail, art. L. 6331-53
A112: Taxe pour le développement de la formation professionnelle dans les métiers de la réparation de l'automobile, du cycle et du motocycle | B112: taxe sur la masse salariale | C112: 3. Les taxes sur la masse salariale | D112: Formation et apprentissage | E112: Taxes sur la main d'œuvre | F112: Fondu dans l’équilibre | H112: 28.8 | I112: ANFA - Association nationale pour la formation automobile | J112: Art. 1609 sexvicies I du code général des impôts
... A116: Contribution spécifique à la formation professionnelle pour Saint Pierre et Miquelon | B116: taxe sur la masse salariale | C116: 3. Les taxes sur la masse salariale | D116: Formation et apprentissage | E116: Taxes sur la main d'œuvre | F116: Fondu dans l’équilibre | H116: 0.3 | I116: France Compétences | J116: Code du travail, art. L. 6523-1-5
A117: Contribution au fonds d'assurance formation des chefs d'entreprise inscrite au répertoire des métiers | B117: taxe sur la masse salariale | C117: 3. Les taxes sur la masse salariale | D117: Formation et apprentissage | E117: Taxes sur la main d'œuvre | F117: Fondu dans l’équilibre | J117: Code du travail, art. L. 6331-48
A118: Financement des congés individuels de formation des salariés sous contrats à durée déterminée CIF-CDD | B118: taxe sur la masse salariale | C118: 3. Les taxes sur la masse salariale | D118: Formation et apprentissage | E118: Taxes sur la main d'œuvre | F118: Fondu dans l’équilibre | J118: Art. L. 6331-6 du code du travail
A119: Participation des employeurs à l'effort de construction (PEEC) | B119: taxe sur la masse salariale | C119: 3. Les taxes sur la masse salariale | D119: Logement des salariés | E119: Taxes sur la main d'œuvre | F119: Fondu dans l’équilibre | H119: 2025.5 | I119: Action Logement Services | J119: Code de la construction et de l'habitation, art. L. 313-1
A120: Prélèvement sur la participation des employeurs à l'effort de construction (PEEC) | B120: taxe sur la masse salariale | C120: 3. Les taxes sur la masse salariale | D120: Logement des salariés | E120: Taxes sur la main d'œuvre | F120: Fondu dans l’équilibre | H120: 6.4 | I120: ANCOLS - Agence nationale de contrôle du logement social | J120: Code de la construction et de l'habitation, art. L. 313-3
A121: Versement transport dû par les entreprises de plus de 11 salariés implantées en province – part IdFM | B121: taxe sur la masse salariale | C121: 3. Les taxes sur la masse salariale | D121: Versement mobilité | E121: Taxes sur la main d'œuvre | F121: Fondu dans l’équilibre | H121: 6652.2 | I121: IdFM - Île-de-France Mobilités | J121: Code général des collectivités territoriales, art. L. 2333-64
A122: Versement transport dû par les entreprises de plus de 11 salariés implantées en province | B122: taxe sur la masse salariale | C122: 3. Les taxes sur la masse salariale | D122: Versement mobilité | E122: Taxes sur la main d'œuvre | F122: Fondu dans l’équilibre | I122: Autorités organisatrices des transports urbains | J122: Code général des collectivités territoriales, art. L. 2333-64
A123: Contribution annuelle au fonds de développement pour l'insertion professionnelle des handicapés (FIPH) | B123: taxe sur la masse salariale | C123: 3. Les taxes sur la masse salariale | D123: Handicap, dialogue social et publics spécifiques | E123: Taxes sur la main d'œuvre | F123: Fondu dans l’équilibre | H123: 507 | I123: Association de gestion du fonds de développement pour l'insertion professionnelle des handicapés (AGEFIPH) | J123: Loi n° 87-517 du 10 juillet 1987 en faveur de l’emploi des travailleurs handicapés, art. L. 5212-1, L. 5212-10, L. 5214-1 et L. 5214-3 du code du travail
A124: Cotisation BTP intempéries | B124: taxe sur la masse salariale | C124: 3. Les taxes sur la masse salariale | D124: Handicap, dialogue social et publics spécifiques | E124: Taxes sur la main d'œuvre | F124: Fondu dans l’équilibre | H124: 128.3 | I124: UCF CIBTP - Union des caisses de France | J124: Art. L. 5424-15, D. 5424-7, D. 5424-29 et D. 5424-36 à D. 5424-41 du code du travail (création) et art. R. 4643-35 à 42 dont le R. 4643-40 du code du travail (affectation)
A125: Contribution patronale au dialogue social (0,016%) | B125: taxe sur la masse salariale | C125: 3. Les taxes sur la masse salariale | D125: Handicap, dialogue social et publics spécifiques | E125: Taxes sur la main d'œuvre | F125: Fondu dans l’équilibre | H125: 123.7 | I125: AGFPN - Association de Gestion du Fonds Paritaire National | J125: Code du travail, art. L. 2135-9
A126: Contribution annuelle au fonds de développement pour l'insertion professionnelle des personnes handicapées dans la fonction publique (FIPHFP) | B126: taxe sur la masse salariale | C126: 3. Les taxes sur la masse salariale | D126: Handicap, dialogue social et publics spécifiques | E126: Taxes sur la main d'œuvre | F126: Fondu dans l’équilibre | H126: 120 | I126: Fonds pour l'insertion des personnes handicapées dans la fonction publique (FIPHFP) | J126: Code général de la fonction publique, art. L. 351-12
A127: Contribution aux unions régionales des professionnels de santé (CURPS) | B127: taxe sur la masse salariale | C127: 3. Les taxes sur la masse salariale | D127: Handicap, dialogue social et publics spécifiques | E127: Taxes sur la main d'œuvre | F127: Fondu dans l’équilibre | J127: Code de la santé publique, art. L. 4031-3
A128: Contribution des diffuseurs d'œuvres au financement de la protection sociale des artistes auteurs | B128: taxe sur la masse salariale | C128: 3. Les taxes sur la masse salariale | D128: Handicap, dialogue social et publics spécifiques | E128: Taxes sur la main d'œuvre | F128: Fondu dans l’équilibre | J128: Code de la sécurité sociale, art. L. 382-4
A129: Cotisations médecine du travail | B129: taxe sur la masse salariale | C129: 3. Les taxes sur la masse salariale | D129: Handicap, dialogue social et publics spécifiques | E129: Taxes sur la main d'œuvre | F129: Fondu dans l’équilibre | J129: Code de la sécurité sociale, art. L. 241-2
A130: Contribution des employeurs à l'association pour la gestion du régime d'assurance des créances des salariés (AGS) | B130: taxe sur la masse salariale | C130: 3. Les taxes sur la masse salariale | D130: Garantie des salaires | E130: Taxes sur la main d'œuvre | F130: Fondu dans l’équilibre | H130: 1747 | I130: AGS - Association pour la gestion du régime d'assurance des créances des salariés | J130: Code du travail, art. L. 143-11-6
A131: Impôt net sur le revenu | B131: impôt ou taxe | C131: 4. Le revenu des personnes | D131: Traitements, salaires et pensions | E131: Ir net | F131: Conservé et absorbe | H131: 130178 | I131: État (budget général) | J131: Code général des impôts, art. 1 A
A132: Autres impôts directs perçus par voie d'émission de rôles | B132: impôt ou taxe | C132: 4. Le revenu des personnes | D132: Traitements, salaires et pensions | E132: Ir net | F132: Fondu par rattachement | G132: Impôt sur le revenu | H132: 2414.3 | I132: Budget général de l'État
A133: CDHR | B133: impôt ou taxe | C133: 4. Le revenu des personnes | D133: Traitements, salaires et pensions | E133: Ir net | F133: Fondu par rattachement | G133: Impôt sur le revenu | H133: 1650 | I133: État (budget général) | J133: Code général des impôts, art. 224
A134: Retenues à la source sur certains bénéfices non commerciaux et de l'impôt sur le revenu | B134: impôt ou taxe | C134: 4. Le revenu des personnes | D134: Traitements, salaires et pensions | E134: Ir net | F134: Fondu par rattachement | G134: Impôt sur le revenu | H134: 1127.9 | I134: État (budget général) | J134: Code général des impôts, art. 182 B
A135: Retenues à la source et prélèvements sur les revenus de capitaux mobiliers et le prélèvement sur les bons anonymes | B135: impôt ou taxe | C135: 4. Le revenu des personnes | D135: Revenus du capital | E135: Ir net | F135: Fondu par rattachement | G135: Impôt sur le revenu | H135: 4800 | I135: État (budget général) | J135: Code général des impôts, art. 119 bis
A136: Taxe sur les transactions financières - fraction affectée de la ressource État | B136: impôt ou taxe | C136: 7. La propriété et les droits d'usage | D136: Mutations et transmissions | E136: Autres taxes sur les produits | F136: Fondu par rattachement | G136: Taxe sur la valeur ajoutée | H136: 2630 | I136: FSD - Fonds de solidarité pour le développement géré par l'Agence française de développement (AFD) - suivi MEAE ; FSD - Fonds de solidarité pour le développement géré par l'Agence française de développement (AFD) - suivi MEFI | J136: Code général des impôts, art. 235 ter ZD
A137: Taxe spéciale due en cas de non-respect de l'engagement de conserver pendant 5 ans les parts de FCPR ou FCPI | B137: impôt ou taxe | C137: 4. Le revenu des personnes | D137: Revenus du capital | E137: Ir net | F137: Fondu par rattachement | G137: Impôt sur le revenu | J137: Art. 1763 B du code général des impôts
A138: Taxe sur les ordres annulés dans le cadre d'opérations à haute fréquence | B138: impôt ou taxe | C138: 7. La propriété et les droits d'usage | D138: Mutations et transmissions | E138: Autres taxes sur les produits | F138: Fondu par rattachement | G138: Taxe sur la valeur ajoutée | J138: Code général des impôts, art. 235 ter ZD bis
A139: Contribution annuelle sur les revenus locatifs | B139: impôt ou taxe | C139: 4. Le revenu des personnes | D139: Revenus fonciers | E139: Ir net | F139: Fondu par rattachement | G139: Impôt sur le revenu | J139: Code général des impôts, art. 234 nonies
A140: Taxe sur la cession à titre onéreux des terrains nus ou des droits relatifs à des terrains nus rendus constructibles du fait de leur classement | B140: impôt ou taxe | C140: 4. Le revenu des personnes | D140: Plus-values des particuliers | E140: Ir net | F140: Fondu par rattachement | G140: Impôt sur le revenu | H140: 17 | I140: ASP - Agence de services et de paiement | J140: Code général des impôts, art. 1605 nonies
A141: Exit tax | B141: impôt ou taxe | C141: 4. Le revenu des personnes | D141: Plus-values des particuliers | E141: Ir net | F141: Fondu par rattachement | G141: Impôt sur le revenu | J141: Code général des impôts, art. 167 bis
A142: Taxe sur les plus-values immobilières (PVI) autres que terrains à bâtir | B142: impôt ou taxe | C142: 4. Le revenu des personnes | D142: Plus-values des particuliers | E142: Ir net | F142: Fondu par rattachement | G142: Impôt sur le revenu | J142: Code général des impôts, art. 1609 nonies G
A143: Impôt sur les sociétés | B143: impôt ou taxe | C143: 5. L'activité des entreprises | D143: Bénéfice des entreprises | E143: Is net | F143: Conservé et absorbe | H143: 84694.4 | I143: État (budget général) | J143: Code général des impôts, art. 205
A144: Contribution sociale de solidarité des sociétés (C3S) | B144: impôt ou taxe | C144: 5. L'activité des entreprises | D144: Bénéfice des entreprises | E144: Taxes sur chiffre d'affaires et bénéfices | F144: Fondu par rattachement | G144: Impôt sur les sociétés | H144: 5452.3 | I144: CNAV | J144: Code de la sécurité sociale, art. L. 137-30
A145: Contribution exceptionnelle sur les bénéfices des entreprises | B145: impôt ou taxe | C145: 5. L'activité des entreprises | D145: Bénéfice des entreprises | E145: Taxes sur chiffre d'affaires et bénéfices | F145: Fondu par rattachement | G145: Impôt sur les sociétés | H145: 4000 | I145: État (budget général) | J145: Art. 48 de la loi n° 2025-127 du 14 février 2025
...

Sheet Par sort
A1: Sort | B1: Prélèvements | C1: Rendement 2026 publié (M€) | D1: Part du rendement publié
A2: Conservé et absorbe | B2: =COUNTIF(Tri!$F$2:$F$421,A2) -> 4 | C2: =SUMIF(Tri!$F$2:$F$421,A2,Tri!$H$2:$H$421) -> 457710.6 | D2: =IFERROR(C2/C$8,0) -> 0.52184242
A3: Fondu par rattachement | B3: =COUNTIF(Tri!$F$2:$F$421,A3) -> 249 | C3: =SUMIF(Tri!$F$2:$F$421,A3,Tri!$H$2:$H$421) -> 302927.3 | D3: =IFERROR(C3/C$8,0) -> 0.34537176
A4: Fondu dans l’équilibre | B4: =COUNTIF(Tri!$F$2:$F$421,A4) -> 32 | C4: =SUMIF(Tri!$F$2:$F$421,A4,Tri!$H$2:$H$421) -> 42645.6 | D4: =IFERROR(C4/C$8,0) -> 0.048620861
A5: Maintenu à part | B5: =COUNTIF(Tri!$F$2:$F$421,A5) -> 51 | C5: =SUMIF(Tri!$F$2:$F$421,A5,Tri!$H$2:$H$421) -> 70843 | D5: =IFERROR(C5/C$8,0) -> 0.080769121
A6: Cotisations sociales à unifier | B6: =COUNTIF(Tri!$F$2:$F$421,A6) -> 81 | C6: =SUMIF(Tri!$F$2:$F$421,A6,Tri!$H$2:$H$421) -> 1317.8 | D6: =IFERROR(C6/C$8,0) -> 0.0015024427
A7: Hors champ | B7: =COUNTIF(Tri!$F$2:$F$421,A7) -> 3 | C7: =SUMIF(Tri!$F$2:$F$421,A7,Tri!$H$2:$H$421) -> 1660.7 | D7: =IFERROR(C7/C$8,0) -> 0.0018933879
A8: Total | B8: =SUM(B2:B7) -> 420 | C8: =SUM(C2:C7) -> 877105

Sheet Par assiette
A1: Assiette | B1: Prélèvements | C1: Rendement 2026 publié (M€) | D1: Part du rendement publié
A2: 1. Les cotisations sociales | B2: =COUNTIF(Tri!$C$2:$C$421,A2) -> 81 | C2: =SUMIF(Tri!$C$2:$C$421,A2,Tri!$H$2:$H$421) -> 1317.8 | D2: =IFERROR(C2/C$10,0) -> 0.0015024427
A3: 2. Les contributions sociales sur les revenus | B3: =COUNTIF(Tri!$C$2:$C$421,A3) -> 18 | C3: =SUMIF(Tri!$C$2:$C$421,A3,Tri!$H$2:$H$421) -> 193247.7 | D3: =IFERROR(C3/C$10,0) -> 0.22032448
A4: 3. Les taxes sur la masse salariale | B4: =COUNTIF(Tri!$C$2:$C$421,A4) -> 30 | C4: =SUMIF(Tri!$C$2:$C$421,A4,Tri!$H$2:$H$421) -> 41750.6 | D4: =IFERROR(C4/C$10,0) -> 0.047600458
A5: 4. Le revenu des personnes | B5: =COUNTIF(Tri!$C$2:$C$421,A5) -> 10 | C5: =SUMIF(Tri!$C$2:$C$421,A5,Tri!$H$2:$H$421) -> 140187.2 | D5: =IFERROR(C5/C$10,0) -> 0.15982944
A6: 5. L'activité des entreprises | B6: =COUNTIF(Tri!$C$2:$C$421,A6) -> 51 | C6: =SUMIF(Tri!$C$2:$C$421,A6,Tri!$H$2:$H$421) -> 106451.9 | D6: =IFERROR(C6/C$10,0) -> 0.12136734
A7: 6. La consommation | B7: =COUNTIF(Tri!$C$2:$C$421,A7) -> 108 | C7: =SUMIF(Tri!$C$2:$C$421,A7,Tri!$H$2:$H$421) -> 324391 | D7: =IFERROR(C7/C$10,0) -> 0.36984284
A8: 7. La propriété et les droits d'usage | B8: =COUNTIF(Tri!$C$2:$C$421,A8) -> 119 | C8: =SUMIF(Tri!$C$2:$C$421,A8,Tri!$H$2:$H$421) -> 68098.1 | D8: =IFERROR(C8/C$10,0) -> 0.077639621
A9: 8. Hors champ | B9: =COUNTIF(Tri!$C$2:$C$421,A9) -> 3 | C9: =SUMIF(Tri!$C$2:$C$421,A9,Tri!$H$2:$H$421) -> 1660.7 | D9: =IFERROR(C9/C$10,0) -> 0.0018933879
A10: Total | B10: =SUM(B2:B9) -> 420 | C10: =SUM(C2:C9) -> 877105

Sheet Par impôt qui reprend
A1: Impôt | B1: Prélèvements | C1: Rendement 2026 publié (M€) | D1: Part du rendement publié
A2: Taxe sur la valeur ajoutée | B2: =COUNTIF(Tri!$G$2:$G$421,A2) -> 109 | C2: =SUMIF(Tri!$G$2:$G$421,A2,Tri!$H$2:$H$421) -> 84182.8 | D2: =IFERROR(C2/C$6,0) -> 0.23094348
A3: Impôt sur le revenu | B3: =COUNTIF(Tri!$G$2:$G$421,A3) -> 23 | C3: =SUMIF(Tri!$G$2:$G$421,A3,Tri!$H$2:$H$421) -> 193108.5 | D3: =IFERROR(C3/C$6,0) -> 0.52976556
A4: Impôt sur les sociétés | B4: =COUNTIF(Tri!$G$2:$G$421,A4) -> 50 | C4: =SUMIF(Tri!$G$2:$G$421,A4,Tri!$H$2:$H$421) -> 21757.5 | D4: =IFERROR(C4/C$6,0) -> 0.059688591
A5: Taxe foncière | B5: =COUNTIF(Tri!$G$2:$G$421,A5) -> 116 | C5: =SUMIF(Tri!$G$2:$G$421,A5,Tri!$H$2:$H$421) -> 65468.1 | D5: =IFERROR(C5/C$6,0) -> 0.17960237
A6: Total | B6: =SUM(B2:B5) -> 298 | C6: =SUM(C2:C5) -> 364516.9
A8: Prélèvements fondus par rattachement et maintenus en complément.

Sheet Par poste du schéma
A1: Poste du schéma de refonte | B1: Montant 2024 (Md€) | C1: Taxes à supprimer (Md€) | D1: Prélèvements | E1: dont fondus | F1: dont maintenus | G1: Rendement 2026 publié (Md€)
A2: TVA | B2: 206.3 | D2: 1 | E2: 0 | F2: 0 | G2: 242.838
A3: Taxes sur la consommation | B3: 105.1 | C3: -26.1 | D3: 0 | E3: 0 | F3: 0 | G3: 0
A4: Dont énergie | B4: 43.7 | C4: -8 | D4: 10 | E4: 3 | F4: 7 | G4: 20.553
A5: Dont alcool, tabac, jeux | B5: 25.6 | C5: -0.3 | D5: 22 | E5: 0 | F5: 22 | G5: 22.897
A6: Dont assurances | B6: 19.2 | D6: 9 | E6: 0 | F6: 9 | G6: 20.203
A7: Dont redevances sur l'eau | B7: 2.2 | C7: -2.2 | D7: 3 | E7: 3 | F7: 0 | G7: 2.675
A8: Dont services de transports | B8: 1.9 | C8: -1.9 | D8: 12 | E8: 12 | F8: 0 | G8: 3.624
A9: Dont véhicules | B9: 3.1 | C9: -6.4 | D9: 9 | E9: 9 | F9: 0 | G9: 3.862
A10: Dont numérique, spectacles | B10: 1.8 | C10: -1.8 | D10: 18 | E10: 18 | F10: 0 | G10: 2.216
A11: Dont autres taxes sur les produits | B11: 4.5 | C11: -4.5 | D11: 19 | E11: 19 | F11: 0 | G11: 6.586
A12: Dont taxe de séjour | B12: 1.1 | D12: 8 | E12: 0 | F12: 8 | G12: 1.346
A13: Dont taxe pollution | B13: 1 | C13: -1 | D13: 2 | E13: 2 | F13: 0 | G13: 1.382
A14: Dont outre-mer | B14: 1.6 | D14: 3 | E14: 0 | F14: 3 | G14: 1.744
A15: Taxes sur la main d'œuvre | B15: 58 | C15: -48 | D15: 32 | E15: 32 | F15: 0 | G15: 42.646
A16: Dont forfaits de cotisation | B16: 8.8 | D16: 2 | E16: 0 | F16: 2 | G16: 9.253
A17: IR net | B17: 87.3 | D17: 10 | E17: 9 | F17: 0 | G17: 140.187
A18: IS net | B18: 57.4 | D18: 1 | E18: 0 | F18: 0 | G18: 84.694
A19: Taxes sur chiffre d'affaires et bénéfices | B19: 10.3 | C19: -10.3 | D19: 15 | E19: 15 | F19: 0 | G19: 13.616
A20: Taxe foncière | B20: 42.9 | D20: 19 | E20: 18 | F20: 0 | G20: 11.642
A21: Autres taxes sur les ménages | B21: 6.5 | C21: -6.7 | D21: 27 | E21: 27 | F21: 0 | G21: 8.213
A22: Autres taxes sur les entreprises | B22: 13.2 | C22: -13.5 | D22: 45 | E22: 45 | F22: 0 | G22: 7.336
A23: Droits de mutation | B23: 37.9 | C23: -32.45 | D23: 5 | E23: 5 | F23: 0 | G23: 0.478
A24: À titre onéreux | B24: 17.1 | C24: -12.05 | D24: 7 | E24: 7 | F24: 0 | G24: 19.28
A25: À titre gratuit | B25: 20.8 | C25: -20.4 | D25: 2 | E25: 2 | F25: 0 | G25: 21.418
A26: Hors schéma — cotisations sociales à unifier | D26: 81 | E26: 0 | F26: 0 | G26: 1.318
A27: Hors schéma — fondu par rattachement | D27: 55 | E27: 55 | F27: 0 | G27: 185.438
A28: Hors schéma — hors champ | D28: 3 | E28: 0 | F28: 0 | G28: 1.661
A30: Montants du schéma : produit 2024 des comptes nationaux (INSEE). Rendements du tri : ce que l’État publie pour 2026. Les deux ne se comparent pas terme à terme.
